{"ts":1770987984684,"data":{"date":"2026-04-04","platform":"TV","images":{"small":"https://lain.bgm.tv/r/200/pic/cover/l/ec/61/552589_CqLqQ.jpg","grid":"https://lain.bgm.tv/r/100/pic/cover/l/ec/61/552589_CqLqQ.jpg","large":"https://lain.bgm.tv/pic/cover/l/ec/61/552589_CqLqQ.jpg","medium":"https://lain.bgm.tv/r/800/pic/cover/l/ec/61/552589_CqLqQ.jpg","common":"https://lain.bgm.tv/r/400/pic/cover/l/ec/61/552589_CqLqQ.jpg"},"summary":"人間の魂を喰らう、妖しく美しい悪魔が降臨――。\r\n\r\n美食の悪魔・カナンは、若くて甘美な魂を食するため、人間界の高校に降り立った。\r\n最初のいけにえに選ばれたのは、一人の男子生徒・供犠羊司。\r\n「私に食べられるなんて、とても光栄なことよ。感謝しなさい、下等生物」\r\n\r\nところが……\r\n\r\nなぜか供犠クンと恋人契約を結ぶことに！？\r\n数千年生きて初恋も未経験の純情なカナンには、毎日がドキドキの連続！\r\n一緒に帰る！？　手を繋ぐ！？　デート！？　\r\n初××！？！？！？！？\r\n\r\n「おのれ\r\n下等生物めーーーーーー！！」\r\n\r\nチョロくてかわいい悪魔の初恋ラブコメ、始まります♪","name":"カナン様はあくまでチョロい","name_cn":"迦楠大人的白给是恶魔级","tags":[{"name":"漫画改","count":26,"total_cont":0},{"name":"StudioKAI","count":18,"total_cont":0},{"name":"恋爱","count":16,"total_cont":0},{"name":"TV","count":16,"total_cont":0},{"name":"2026","count":15,"total_cont":0},{"name":"喜剧","count":14,"total_cont":0},{"name":"2026年4月","count":9,"total_cont":0},{"name":"2026年","count":9,"total_cont":0},{"name":"日本","count":8,"total_cont":0},{"name":"漫改","count":7,"total_cont":0},{"name":"TVA","count":6,"total_cont":0},{"name":"校园","count":5,"total_cont":0},{"name":"日常","count":5,"total_cont":0},{"name":"后宫","count":3,"total_cont":0},{"name":"未定档","count":3,"total_cont":0},{"name":"室谷靖","count":3,"total_cont":0},{"name":"日本动画","count":2,"total_cont":0},{"name":"スタジオKAI","count":2,"total_cont":0},{"name":"古賀葵","count":2,"total_cont":0},{"name":"山下誠一郎","count":2,"total_cont":0},{"name":"日画","count":1,"total_cont":0},{"name":"2026春","count":1,"total_cont":0},{"name":"古贺葵","count":1,"total_cont":0},{"name":"青春","count":1,"total_cont":0},{"name":"池田臨太郎","count":1,"total_cont":0}],"infobox":[{"key":"中文名","value":"迦楠大人的白给是恶魔级"},{"key":"别名","value":[{"v":"容易对付的恶魔大人"},{"v":"Kanan-sama wa Akumade Choroi"}]},{"key":"话数","value":"*"},{"key":"放送开始","value":"2026年4月4日"},{"key":"放送星期","value":"星期六"},{"key":"官方网站","value":"https://kanachoro-anime.com/"},{"key":"播放电视台","value":"TOKYO MX"},{"key":"其他电视台","value":"BS11"},{"key":"导演","value":"室谷靖"},{"key":"音乐","value":"睦月周平"},{"key":"Copyright","value":"©nonco・講談社／「カナン様はあくまでチョロい製作委員会」"},{"key":"原作","value":"nonco（講談社「週刊少年マガジン」連載中）"},{"key":"人物设定","value":"皆川愛香利"}],"rating":{"rank":0,"total":0,"count":{"1":0,"2":0,"3":0,"4":0,"5":0,"6":0,"7":0,"8":0,"9":0,"10":0},"score":0},"total_episodes":12,"collection":{"on_hold":4,"dropped":3,"wish":273,"collect":3,"doing":9},"id":552589,"eps":0,"meta_tags":["喜剧","TV","恋爱","日本","漫画改"],"volumes":0,"series":false,"locked":false,"nsfw":false,"type":2}}