{"ts":1772017392417,"data":{"date":"2026-01-10","platform":"TV","images":{"small":"https://lain.bgm.tv/r/200/pic/cover/l/86/7c/543772_Io88u.jpg","grid":"https://lain.bgm.tv/r/100/pic/cover/l/86/7c/543772_Io88u.jpg","large":"https://lain.bgm.tv/pic/cover/l/86/7c/543772_Io88u.jpg","medium":"https://lain.bgm.tv/r/800/pic/cover/l/86/7c/543772_Io88u.jpg","common":"https://lain.bgm.tv/r/400/pic/cover/l/86/7c/543772_Io88u.jpg"},"summary":"死者的SNS帐号会怎么样呢？那些留下未缘的亡者帐号，最终会化为数位幽灵──『化垢』，重新在现世现身。\r\n为了替妹妹绯里筹措治疗费，缘城苍吏以炎上系实况主「青蓝苹果」的身份每天进行直播活动。然而，因某个契机觉醒了电能的缘城，被带往谣言不断的「弥电学园」。那是一所随着网路普及而诞生，专门培养能驱除数位化幽灵的新世代灵媒师的学园！\r\n燃烧、击碎、驱除──现代式除灵战斗正式开幕！\r\n\r\n[简介原文]\r\n死者のSNSアカウントってどうなると思う？\r\n未練を残した「亡者のアカウント」（デッドアカウント）は、やがてデジタルの幽霊――化け垢として現世へ蘇る……。\r\n縁城蒼吏は、妹・緋里の治療費を稼ぐため、炎上系配信者『煽りんご』として日々配信活動をしていた。\r\nしかし、とあるきっかけで電能に開眼した縁城は、怪しい噂の絶えない『弥電学園』へと連れられる。\r\nそこはインターネットの普及と共にデジタル化してしまった幽霊を祓う、新時代の霊媒師を育てる学園だった！\r\n燃やして叩いて祓う、現代式除霊バトルアクション開幕！","name":"デッドアカウント","name_cn":"死亡账号","tags":[{"name":"2026年1月","count":179,"total_cont":0},{"name":"漫画改","count":129,"total_cont":0},{"name":"战斗","count":119,"total_cont":0},{"name":"奇幻","count":94,"total_cont":0},{"name":"SynergySP","count":82,"total_cont":0},{"name":"TV","count":78,"total_cont":0},{"name":"2026","count":60,"total_cont":0},{"name":"日本","count":46,"total_cont":0},{"name":"漫改","count":44,"total_cont":0},{"name":"互联网","count":37,"total_cont":0},{"name":"讲谈社","count":29,"total_cont":0},{"name":"动作","count":25,"total_cont":0},{"name":"齐藤启也","count":13,"total_cont":0},{"name":"热血","count":9,"total_cont":0},{"name":"动画","count":7,"total_cont":0},{"name":"斉藤啓也","count":4,"total_cont":0},{"name":"怪谈","count":3,"total_cont":0},{"name":"都市","count":3,"total_cont":0},{"name":"2026年","count":2,"total_cont":0},{"name":"少年向","count":2,"total_cont":0},{"name":"日本动画","count":2,"total_cont":0},{"name":"冬季番","count":1,"total_cont":0},{"name":"花江夏樹","count":1,"total_cont":0},{"name":"TV-01","count":1,"total_cont":0},{"name":"搞笑","count":1,"total_cont":0},{"name":"熱血","count":1,"total_cont":0},{"name":"缝合怪","count":1,"total_cont":0},{"name":"内山昂輝","count":1,"total_cont":0},{"name":"2020-2029","count":1,"total_cont":0},{"name":"戰鬥","count":1,"total_cont":0}],"infobox":[{"key":"中文名","value":"死亡账号"},{"key":"别名","value":[{"v":"死亡帳號"},{"v":"Dead Account"}]},{"key":"话数","value":"12"},{"key":"放送开始","value":"2026年1月10日"},{"key":"放送星期","value":"星期六"},{"key":"官方网站","value":"https://dead-account.com/"},{"key":"播放电视台","value":"テレビ朝日系全国24局ネット“IMAnimation”枠"},{"key":"导演","value":"斉藤啓也"},{"key":"音乐","value":"井内啓二"},{"key":"Copyright","value":"©渡辺静・講談社／「デッドアカウント」製作委員会"},{"key":"原作","value":"渡辺静（講談社「マガジンポケット」連載）"},{"key":"美术设计","value":"伊良波理沙"},{"key":"设定","value":"福井麻記、船道愛子"},{"key":"特效作画监督","value":"特效监修：久保充照"},{"key":"製作","value":"「デッドアカウント」製作委員会（日本コロムビア、講談社、テレビ朝日、サミー、Crunchyroll、SynergySP、ブシロードムーブ、スタジオマウス）"},{"key":"企画","value":"土門義隆、高島祐一郎、小野仁、星野歩、末平アサ、加藤良太、一杉武"},{"key":"执行制片人","value":"北田展久、古川慎、白倉由紀子"},{"key":"制片人","value":"天野大地、秋田規行、岩田皐希、加瀨直人、黒須信彦、天野賢、大貫祐介"},{"key":"动画制片人","value":"熊谷侑也"},{"key":"副制片人","value":"山下健太、清家綾香、村瀬了介、牧野武尊、鈴木雅人"},{"key":"宣传制片人","value":"小松美国"},{"key":"助理制片人","value":"佐々木祐哉、"},{"key":"制作管理","value":"渡邊千城"},{"key":"设定制作","value":"金田卓洋"},{"key":"制作进行","value":"増田卓也"},{"key":"主题歌演出","value":"五十嵐ハル / 金子みゆ"},{"key":"主题歌作词","value":"五十嵐ハル / 芦田菜名子、金子みゆ"},{"key":"主题歌作曲","value":"五十嵐ハル / JaysicK、芦田菜名子"},{"key":"主题歌编曲","value":"五十嵐ハル、石田勇喜 / JaysicK"},{"key":"摄影监督助理","value":"大津美紗子"},{"key":"特效","value":"村上宜隆、杨怡"},{"key":"3DCG","value":"旭プロダクション"},{"key":"CG 制作人","value":"露木祐治"},{"key":"CG 导演","value":"古屋和人"},{"key":"2D 设计","value":"高橋倫太郎、田村あず紗、増田咲紀"},{"key":"在线剪辑","value":"Imagica EMS（宮井堂行）"},{"key":"音效","value":"川田清貴"},{"key":"录音","value":"徳久智成"},{"key":"录音助理","value":"吉田陵人"},{"key":"录音工作室","value":"STUDIO MAUSU（スタジオマウス）"},{"key":"音响","value":"スタジオマウス"},{"key":"音响制作担当","value":"与那霸彩"},{"key":"音乐制作","value":"日本コロムビア；音乐制作协力：Stem Music；音乐协力：テレビ朝日ミュージック"},{"key":"OP・ED 分镜","value":"桂田佳孝（OP&ED）"},{"key":"OP・ED 演出","value":"桂田佳孝（OP&ED）"}],"rating":{"rank":9641,"total":315,"count":{"1":5,"2":12,"3":37,"4":94,"5":104,"6":51,"7":5,"8":4,"9":1,"10":2},"score":4.6},"total_episodes":12,"collection":{"on_hold":62,"dropped":353,"wish":323,"collect":47,"doing":844},"id":543772,"eps":12,"meta_tags":["TV","日本","奇幻","漫画改","战斗"],"volumes":0,"series":false,"locked":false,"nsfw":false,"type":2}}